git_root/__init__.py
git_root/git_root.py
git_root-0.1.dist-info/LICENSE
git_root-0.1.dist-info/METADATA
git_root-0.1.dist-info/WHEEL
git_root-0.1.dist-info/top_level.txt
git_root-0.1.dist-info/RECORD
