Metadata-Version: 2.1
Name: git-root
Version: 0.1
Summary: Find the root of your git repo
Home-page: https://github.com/jtilly/git_root
Author: Jan Tilly
Author-email: jantilly@gmail.com
License: UNKNOWN
Platform: UNKNOWN
